sibi/__init__.py
sibi/applications.py
sibi/decorators.py
sibi/exceptions.py
sibi/ib_factory.py
sibi/ib_protocol.py
sibi/ibapi/__init__.py
sibi/ibapi/account_summary_tags.py
sibi/ibapi/client.py
sibi/ibapi/comm.py
sibi/ibapi/commission_report.py
sibi/ibapi/common.py
sibi/ibapi/connection.py
sibi/ibapi/contract.py
sibi/ibapi/decoder.py
sibi/ibapi/enum_implem.py
sibi/ibapi/errors.py
sibi/ibapi/execution.py
sibi/ibapi/message.py
sibi/ibapi/news.py
sibi/ibapi/object_implem.py
sibi/ibapi/order.py
sibi/ibapi/order_condition.py
sibi/ibapi/order_state.py
sibi/ibapi/orderdecoder.py
sibi/ibapi/reader.py
sibi/ibapi/scanner.py
sibi/ibapi/server_versions.py
sibi/ibapi/softdollartier.py
sibi/ibapi/tag_value.py
sibi/ibapi/ticktype.py
sibi/ibapi/utils.py
sibi/ibapi/wrapper.py
sibi/main.py
sibi/models.py
sibi/xmlrpc_server.py
sibi-0.1.6.dist-info/entry_points.txt
sibi-0.1.6.dist-info/WHEEL
sibi-0.1.6.dist-info/METADATA
sibi-0.1.6.dist-info/RECORD
